<?xml version="1.0" encoding="UTF-8" standalone="no"?>
<academia>
    <alumno cCodALu="001" cNomAlu="Antonio">
        <matricula>
            <codigo_curso>C002</codigo_curso>
            <nombre_curso>Chino Intermedio</nombre_curso>
            <nota_media>0</nota_media>
        </matricula>
        <matricula>
            <codigo_curso>F001</codigo_curso>
            <nombre_curso>Frances Basico</nombre_curso>
            <nota_media>0</nota_media>
        </matricula>
        <matricula>
            <codigo_curso>I001</codigo_curso>
            <nombre_curso>Ingles Basico</nombre_curso>
            <nota_media>0</nota_media>
        </matricula>
        <matricula>
            <codigo_curso>I002</codigo_curso>
            <nombre_curso>Ingles Intermedio</nombre_curso>
            <nota_media>0</nota_media>
        </matricula>
        <matricula>
            <codigo_curso>I003</codigo_curso>
            <nombre_curso>Ingles Avanzado</nombre_curso>
            <nota_media>0</nota_media>
        </matricula>
    </alumno>
    <alumno cCodALu="002" cNomAlu="Maria">
        <matricula>
            <codigo_curso>C002</codigo_curso>
            <nombre_curso>Chino Intermedio</nombre_curso>
            <nota_media>0</nota_media>
        </matricula>
        <matricula>
            <codigo_curso>F001</codigo_curso>
            <nombre_curso>Frances Basico</nombre_curso>
            <nota_media>0</nota_media>
        </matricula>
        <matricula>
            <codigo_curso>I001</codigo_curso>
            <nombre_curso>Ingles Basico</nombre_curso>
            <nota_media>3</nota_media>
        </matricula>
        <matricula>
            <codigo_curso>I002</codigo_curso>
            <nombre_curso>Ingles Intermedio</nombre_curso>
            <nota_media>2</nota_media>
        </matricula>
        <matricula>
            <codigo_curso>I003</codigo_curso>
            <nombre_curso>Ingles Avanzado</nombre_curso>
            <nota_media>0</nota_media>
        </matricula>
    </alumno>
</academia>
